README.md
setup.py
coralinedb/__init__.py
coralinedb/coraline_mssql.py
coralinedb/coraline_mysql.py
coralinedb/coraline_postgresql.py
coralinedb/coralinedb.py
coralinedb/utils.py
coralinedb/version.py
coralinedb.egg-info/PKG-INFO
coralinedb.egg-info/SOURCES.txt
coralinedb.egg-info/dependency_links.txt
coralinedb.egg-info/entry_points.txt
coralinedb.egg-info/top_level.txt