Metadata-Version: 1.2
Name: coralinedb
Version: 2.10
Summary: Coraline Database Manager Package
Home-page: https://www.coraline.co.th
Author: Jiranun J.
Author-email: jiranun@coraline.co.th
License: UNKNOWN
Keywords: mysql,database,db,coraline,mssql,data,postgresql,postgres
Platform: UNKNOWN
Classifier: Programming Language :: Python
Classifier: Programming Language :: SQL
Classifier: Development Status :: 4 - Beta
Classifier: Intended Audience :: Developers
Classifier: Intended Audience :: Science/Research
Classifier: License :: OSI Approved :: MIT License
Classifier: Natural Language :: English
Classifier: Topic :: Database
Requires-Python: >=3.6
